lnt/__init__.py
lnt/cli.py
lnt/constants.py
lnt/utils.py
lnt/validators.py
lnt/commands/__init__.py
lnt/commands/create.py
lnt/commands/kill.py
lnt/commands/view.py
lnt/commands/utils/__init__.py
lnt/commands/utils/rebal.py
lnt/commands/utils/utils.py
lnt/graphics/__init__.py
lnt/graphics/styles.py
lnt/graphics/utils.py
lnt/rpc/api.py
lnt/rpc/rpc_pb2.py
lnt/rpc/rpc_pb2_grpc.py
lnt-1.1.1.dist-info/LICENSE
lnt-1.1.1.dist-info/METADATA
lnt-1.1.1.dist-info/WHEEL
lnt-1.1.1.dist-info/entry_points.txt
lnt-1.1.1.dist-info/top_level.txt
lnt-1.1.1.dist-info/RECORD
