Metadata-Version: 2.1
Name: lnt
Version: 1.1.1
Summary: UNKNOWN
Home-page: https://github.com/thesis/lnt
Author: arshbot
Author-email: harshagoli@gmail.com
License: UNKNOWN
Platform: UNKNOWN
Requires-Dist: click
Requires-Dist: grpcio-tools
Requires-Dist: grpcio
Requires-Dist: PyInquirer
Requires-Dist: googleapis-common-protos
Requires-Dist: requests
